Workbook
Name aporte: APP!$D$17
Name investimento_acumulado: APP!$D$20
Name patrimonio_acumulado: APP!$D$21
Name rendimento_carteira: APP!$D$13
Name salario_mensal: APP!$D$12
Name sugestao_investimento: APP!$D$14
Name taxa_mensal: APP!$D$19
Name tempo_estimado: APP!$D$18

Sheet APP
B11: CONFIGURAÇÕES
B12: Salário | D12: 30000
B13: Rendimento Carteira | D13: 0.01
B14: Sugestão de Investimento (30%) | D14: =D12*30% -> 9000
B16: INVESTIMENTO MENSAL
B17: Investimento mensal | D17: 10000
B18: Período em Anos | D18: 5
B19: Taxa de Rendimento Mensal | D19: 0.01
B20: Investimento Acumulado | D20: =FV(0,tempo_estimado*12,aporte*-1) -> 600000
B21: Patrimônio Acumulado Projetado | D21: =FV(taxa_mensal,tempo_estimado*12,aporte*-1) -> 816696.7
B22: Dividendo Mensal | D22: =patrimonio_acumulado*rendimento_carteira -> 8166.967
B24: CENÁRIO | D24: Dividendo | F24: PRAZO | G24: CENÁRIO
A25: 2 | B25: Patrimônio Acumulado em 2 anos | C25: =FV($D$19,$A25*12,$D$17*-1) -> 269734.65 | D25: =C25*rendimento_carteira -> 2697.3465 | G25: Patrimônio acumulado | H25: Dividendo mensal
A26: 5 | B26: Patrimônio Acumulado em 5 anos | C26: =FV($D$19,$A26*12,$D$17*-1) -> 816696.7 | D26: =C26*rendimento_carteira -> 8166.967 | F26: 2 anos | G26: =C25 -> 269734.65 | H26: =D25 -> 2697.3465
A27: 10 | B27: Patrimônio Acumulado em 10 anos | C27: =FV($D$19,$A27*12,$D$17*-1) -> 2300386.9 | D27: =C27*rendimento_carteira -> 23003.869 | F27: 5 anos | G27: =C26 -> 816696.7 | H27: =D26 -> 8166.967
A28: 20 | B28: Patrimônio Acumulado em 20 anos | C28: =FV($D$19,$A28*12,$D$17*-1) -> 9892553.7 | D28: =C28*rendimento_carteira -> 98925.537 | F28: 10 anos | G28: =C27 -> 2300386.9 | H28: =D27 -> 23003.869
A29: 30 | B29: Patrimônio Acumulado em 30 anos | C29: =FV($D$19,$A29*12,$D$17*-1) -> 34949641 | D29: =C29*rendimento_carteira -> 349496.41 | F29: 20 anos | G29: =C28 -> 9892553.7 | H29: =D28 -> 98925.537
F30: 30 anos | G30: =C29 -> 34949641 | H30: =D29 -> 349496.41
B47: PERFIL | C47: AGRESSIVO
B48: VALOR A SER INVESTIDO POR MÊS | C48: =aporte -> 10000
B50: TIPO DE FII | C50: PERCENTUAL SUGERIDO | D50: VALORES
B51: PAPEL | C51: =VLOOKUP($C$47&"-"&B51,'TABELA DE APOIO'!$B:$E,4,FALSE) -> 0.5 | D51: =C51*$C$48 -> 5000
B52: TIJOLO | C52: =VLOOKUP($C$47&"-"&B52,'TABELA DE APOIO'!$B:$E,4,FALSE) -> 0.1 | D52: =C52*$C$48 -> 1000
B53: HÍBRIDO | C53: =VLOOKUP($C$47&"-"&B53,'TABELA DE APOIO'!$B:$E,4,FALSE) -> 0.05 | D53: =C53*$C$48 -> 500
B54: FOFs | C54: =VLOOKUP($C$47&"-"&B54,'TABELA DE APOIO'!$B:$E,4,FALSE) -> 0.05 | D54: =C54*$C$48 -> 500
B55: DESENVOLVIMENTO | C55: =VLOOKUP($C$47&"-"&B55,'TABELA DE APOIO'!$B:$E,4,FALSE) -> 0.2 | D55: =C55*$C$48 -> 2000
B56: HOTELARIA | C56: =VLOOKUP($C$47&"-"&B56,'TABELA DE APOIO'!$B:$E,4,FALSE) -> 0.1 | D56: =C56*$C$48 -> 1000
D57: =SUM(D51:D56) -> 10000

Sheet TABELA DE APOIO
B3: CHAVE | C3: PERFIL | D3: TIPO DE FII | E3: % | H3: %
B4: =C4&"-"&D4 -> CONSERVADOR-PAPEL | C4: CONSERVADOR | D4: PAPEL | E4: 0.3 | G4: MODERADO-TIJOLO | H4: =VLOOKUP(G4,$B:$E,4,FALSE) -> 0.35
B5: =C5&"-"&D5 -> CONSERVADOR-TIJOLO | C5: CONSERVADOR | D5: TIJOLO | E5: 0.5
B6: =C6&"-"&D6 -> CONSERVADOR-HÍBRIDO | C6: CONSERVADOR | D6: HÍBRIDO | E6: 0.1
B7: =C7&"-"&D7 -> CONSERVADOR-FOFs | C7: CONSERVADOR | D7: FOFs | E7: 0.1
B8: =C8&"-"&D8 -> CONSERVADOR-DESENVOLVIMENTO | C8: CONSERVADOR | D8: DESENVOLVIMENTO | E8: 0
B9: =C9&"-"&D9 -> CONSERVADOR-HOTELARIA | C9: CONSERVADOR | D9: HOTELARIA | E9: 0
B10: =C10&"-"&D10 -> MODERADO-PAPEL | C10: MODERADO | D10: PAPEL | E10: 0.32
B11: =C11&"-"&D11 -> MODERADO-TIJOLO | C11: MODERADO | D11: TIJOLO | E11: 0.35
B12: =C12&"-"&D12 -> MODERADO-HÍBRIDO | C12: MODERADO | D12: HÍBRIDO | E12: 0.08
B13: =C13&"-"&D13 -> MODERADO-FOFs | C13: MODERADO | D13: FOFs | E13: 0.05
B14: =C14&"-"&D14 -> MODERADO-DESENVOLVIMENTO | C14: MODERADO | D14: DESENVOLVIMENTO | E14: 0.1
B15: =C15&"-"&D15 -> MODERADO-HOTELARIA | C15: MODERADO | D15: HOTELARIA | E15: 0.1
B16: =C16&"-"&D16 -> AGRESSIVO-PAPEL | C16: AGRESSIVO | D16: PAPEL | E16: 0.5
... B21: =C21&"-"&D21 -> AGRESSIVO-HOTELARIA | C21: AGRESSIVO | D21: HOTELARIA | E21: 0.1

Sheet TIPOS DE FII
B3: TIPOS DE FUNDOS IMOBILIÁRIOS
B4: Explicações simples das categorias usadas no arquivo original da Empresa B3 (Bolsa de Valores). Um fundo pode ter características próprias; confira sempre os documentos oficiais.
B6: TIPO | C6: EXPLICAÇÃO | D6: DE ONDE PODE VIR A RENDA | E6: RISCOS A ANALISAR
B7: Papel | C7: Investe principalmente em títulos e créditos ligados ao setor imobiliário, como CRIs. | D7: Juros e pagamentos de títulos ligados ao mercado imobiliário, como CRIs. | E7: Inadimplência, risco de crédito e mudanças nos juros e na inflação.
B8: Tijolo | C8: Investe em imóveis físicos, como galpões, shoppings, escritórios ou centros de distribuição. | D8: Aluguéis de imóveis, como galpões, escritórios e shoppings. | E8: Imóveis vagos, saída de inquilinos e queda no valor das cotas.
B9: Híbrido | C9: Combina diferentes estratégias, por exemplo imóveis e títulos imobiliários. | D9: Combinação de imóveis e ativos financeiros imobiliários. | E9: Combinação dos riscos das diferentes estratégias.
B10: FOFs (fundo de fundos) | C10: Compra cotas de outros fundos imobiliários em vez de concentrar tudo em imóveis próprios. | D10: Rendimentos e variações de valor de cotas de outros FIIs. | E10: Oscilação dos fundos investidos e custos da estrutura.
B11: Desenvolvimento | C11: Investe em projetos imobiliários em construção ou desenvolvimento. | D11: Possíveis ganhos com construção e venda ou exploração de imóveis. | E11: Atrasos, custos maiores e dificuldade de vender ou alugar.
B12: Hotelaria | C12: Investe em hotéis ou ativos relacionados à hospedagem, conforme a estratégia do fundo. | D12: Resultado da operação ou da exploração de empreendimentos hoteleiros. | E12: Ocupação, sazonalidade e desempenho do setor.
B14: Importante: as categorias ajudam a entender a estratégia, mas não dizem sozinhas se um fundo é seguro ou adequado. Avalie a qualidade dos ativos, a gestão, os contratos, a diversificação, a liquidez, os custos e os riscos descritos nos documentos do fundo.
